{
  "meta": {
    "id": "manual-world",
    "kind": "manual",
    "version": 1,
    "description": "Hand-authored chapter slice world, player, item, skill, and state definitions."
  },
  "maps": [
    {
      "id": "town",
      "name": "Lou Sang Village",
      
      "width": 20,
      "height": 14,
      "tileWidth": 16,
      "tileHeight": 16,
      "tileLayers": [
        {
          "id": "ground",
          "name": "Ground",
          "width": 20,
          "height": 14,
          "tiles": [
            3,3,3,3,3,3,3,3,3,3,3,3,3,3,3,3,3,3,3,3,
            3,1,1,1,1,1,1,1,1,1,2,1,1,1,1,1,1,1,1,3,
            3,1,1,1,1,1,1,1,1,1,2,1,1,1,1,1,1,1,1,3,
            3,1,1,1,3,3,3,1,1,1,2,1,1,3,3,3,1,1,1,3,
            3,1,1,1,3,3,3,1,1,1,2,1,1,3,3,3,1,1,1,3,
            3,1,1,1,3,3,3,1,1,1,2,1,1,3,3,3,1,1,1,3,
            3,1,1,1,1,1,1,1,1,1,2,1,1,1,1,1,1,1,1,3,
            3,1,1,1,1,1,1,1,1,1,2,1,1,1,1,1,1,1,1,3,
            3,2,2,2,2,2,2,2,2,2,2,2,2,2,2,2,2,2,2,3,
            3,1,1,1,1,1,1,1,1,1,2,1,1,1,1,1,1,1,1,3,
            3,1,1,1,1,1,1,1,1,1,2,1,1,1,1,1,1,1,1,3,
            3,1,1,1,3,3,1,1,1,1,2,1,1,1,3,3,1,1,1,3,
            3,1,1,1,1,1,1,1,1,1,2,1,1,1,1,1,1,1,1,3,
            3,3,3,3,3,3,3,3,3,3,3,3,3,3,3,3,3,3,3,3
          ]
        }
      ],
      "collisionLayers": [
        {
          "id": "collision",
          "name": "Collision",
          "width": 20,
          "height": 14,
          "blocked": [
            1,1,1,1,1,1,1,1,1,1,1,1,1,1,1,1,1,1,1,1,
            1,0,0,0,0,0,0,0,0,0,0,0,0,0,0,0,0,0,0,1,
            1,0,0,0,0,0,0,0,0,0,0,0,0,0,0,0,0,0,0,1,
            1,0,0,0,1,1,1,0,0,0,0,0,0,1,1,1,0,0,0,1,
            1,0,0,0,1,1,1,0,0,0,0,0,0,1,1,1,0,0,0,1,
            1,0,0,0,1,1,1,0,0,0,0,0,0,1,1,1,0,0,0,1,
            1,0,0,0,0,0,0,0,0,0,0,0,0,0,0,0,0,0,0,1,
            1,0,0,0,0,0,0,0,0,0,0,0,0,0,0,0,0,0,0,1,
            1,0,0,0,0,0,0,0,0,0,0,0,0,0,0,0,0,0,0,1,
            1,0,0,0,0,0,0,0,0,0,0,0,0,0,0,0,0,0,0,1,
            1,0,0,0,0,0,0,0,0,0,0,0,0,0,0,0,0,0,0,1,
            1,0,0,0,1,1,0,0,0,0,0,0,0,0,1,1,0,0,0,1,
            1,0,0,0,0,0,0,0,0,0,0,0,0,0,0,0,0,0,0,1,
            1,1,1,1,1,1,1,1,1,1,1,1,1,1,1,1,1,1,1,1
          ]
        }
      ],
      "portals": [],
      "spawnPoints": [
        {
          "id": "town-start",
          "x": 10,
          "y": 10,
          "facing": "down"
        },
        {
          "id": "from-field",
          "x": 17,
          "y": 8,
          "facing": "left"
        }
      ],
      "npcs": [
        {
          "id": "town-guard",
          "name": "Gate Watch",
          "x": 16,
          "y": 8,
          "sprite": "guard",
          "facing": "left",
          "behavior": "idle"
        },
        {
          "id": "merchant",
          "name": "Supply Keeper",
          "x": 12,
          "y": 7,
          "sprite": "merchant",
          "facing": "left",
          "behavior": "idle",
          "shopId": "starter-shop"
        },
        {
          "id": "village-guide",
          "name": "Village Elder",
          "x": 8,
          "y": 7,
          "sprite": "guide",
          "facing": "down",
          "behavior": "idle"
        }
      ],
      "triggers": [
        {
          "id": "lou-sang-guard-trigger",
          "kind": "npcInteraction",
          "npcId": "town-guard",
          "eventId": "lou-sang-guard-event",
          "once": false
        },
        {
          "id": "lou-sang-shop-trigger",
          "kind": "npcInteraction",
          "npcId": "merchant",
          "eventId": "lou-sang-shop-event",
          "once": false
        },
        {
          "id": "guide-talk-trigger",
          "kind": "npcInteraction",
          "npcId": "village-guide",
          "eventId": "intro-event",
          "once": false
        },
        {
          "id": "lou-sang-chest-trigger",
          "kind": "tile",
          "x": 3,
          "y": 11,
          "width": 1,
          "height": 1,
          "eventId": "lou-sang-chest-event",
          "once": true
        },
        {
          "id": "lou-sang-east-exit-trigger",
          "kind": "tile",
          "x": 18,
          "y": 8,
          "width": 1,
          "height": 1,
          "eventId": "lou-sang-east-exit-event",
          "once": false
        }
      ]
    },
    {
      "id": "field",
      "name": "Eastern Field",
      "width": 24,
      "height": 14,
      "tileWidth": 16,
      "tileHeight": 16,
      "tileLayers": [
        {
          "id": "ground",
          "name": "Ground",
          "width": 24,
          "height": 14,
          "tiles": [
            3,3,3,3,3,3,3,3,3,3,3,3,3,3,3,3,3,3,3,3,3,3,3,3,
            3,1,1,1,1,1,1,1,1,1,1,1,1,1,1,1,1,1,1,1,1,1,1,3,
            3,1,1,1,1,1,1,1,1,1,1,1,1,1,1,1,1,1,1,1,1,1,1,3,
            3,1,1,1,1,1,1,1,1,1,4,4,4,4,1,1,1,1,1,1,1,1,1,3,
            3,1,1,1,1,1,1,1,1,1,4,4,4,4,1,1,1,1,1,1,1,1,1,3,
            3,1,1,1,1,1,1,1,1,1,4,4,4,4,1,1,1,1,1,1,1,1,1,3,
            3,1,1,1,1,1,1,1,1,1,1,1,1,1,1,1,1,1,1,1,1,1,1,3,
            3,2,2,2,2,2,2,2,2,2,2,2,2,2,2,2,2,2,2,2,2,2,2,3,
            3,1,1,1,1,1,1,1,1,1,1,1,1,1,1,1,1,1,1,1,1,1,1,3,
            3,1,1,1,1,1,1,1,1,1,1,1,1,1,1,1,3,3,3,1,1,1,1,3,
            3,1,1,1,1,1,1,1,1,1,1,1,1,1,1,1,3,3,3,1,1,1,1,3,
            3,1,1,1,1,1,1,1,1,1,1,1,1,1,1,1,1,1,1,1,1,1,1,3,
            3,1,1,1,1,1,1,1,1,1,1,1,1,1,1,1,1,1,1,1,1,1,1,3,
            3,3,3,3,3,3,3,3,3,3,3,3,3,3,3,3,3,3,3,3,3,3,3,3
          ]
        }
      ],
      "collisionLayers": [
        {
          "id": "collision",
          "name": "Collision",
          "width": 24,
          "height": 14,
          "blocked": [
            1,1,1,1,1,1,1,1,1,1,1,1,1,1,1,1,1,1,1,1,1,1,1,1,
            1,0,0,0,0,0,0,0,0,0,0,0,0,0,0,0,0,0,0,0,0,0,0,1,
            1,0,0,0,0,0,0,0,0,0,0,0,0,0,0,0,0,0,0,0,0,0,0,1,
            1,0,0,0,0,0,0,0,0,0,1,1,1,1,0,0,0,0,0,0,0,0,0,1,
            1,0,0,0,0,0,0,0,0,0,1,1,1,1,0,0,0,0,0,0,0,0,0,1,
            1,0,0,0,0,0,0,0,0,0,1,1,1,1,0,0,0,0,0,0,0,0,0,1,
            1,0,0,0,0,0,0,0,0,0,0,0,0,0,0,0,0,0,0,0,0,0,0,1,
            1,0,0,0,0,0,0,0,0,0,0,0,0,0,0,0,0,0,0,0,0,0,0,1,
            1,0,0,0,0,0,0,0,0,0,0,0,0,0,0,0,0,0,0,0,0,0,0,1,
            1,0,0,0,0,0,0,0,0,0,0,0,0,0,0,0,1,1,1,0,0,0,0,1,
            1,0,0,0,0,0,0,0,0,0,0,0,0,0,0,0,1,1,1,0,0,0,0,1,
            1,0,0,0,0,0,0,0,0,0,0,0,0,0,0,0,0,0,0,0,0,0,0,1,
            1,0,0,0,0,0,0,0,0,0,0,0,0,0,0,0,0,0,0,0,0,0,0,1,
            1,1,1,1,1,1,1,1,1,1,1,1,1,1,1,1,1,1,1,1,1,1,1,1
          ]
        }
      ],
      "portals": [
        {
          "id": "to-town",
          "x": 1,
          "y": 7,
          "width": 1,
          "height": 1,
          "targetMapId": "town",
          "targetSpawnId": "from-field"
        }
      ],
      "spawnPoints": [
        {
          "id": "field-gate",
          "x": 2,
          "y": 7,
          "facing": "right"
        },
        {
          "id": "from-east-road",
          "x": 21,
          "y": 7,
          "facing": "left"
        }
      ],
      "npcs": [
        {
          "id": "field-patrol",
          "name": "巡逻兵",
          "x": 9,
          "y": 7,
          "sprite": "guard",
          "facing": "right",
          "behavior": "idle"
        }
      ],
      "triggers": [
        {
          "id": "field-east-road-trigger",
          "kind": "tile",
          "x": 22,
          "y": 7,
          "width": 1,
          "height": 1,
          "eventId": "field-east-road-event",
          "once": false
        },
        {
          "id": "field-battle-trigger",
          "kind": "region",
          "x": 10,
          "y": 6,
          "width": 4,
          "height": 3,
          "encounterTableId": "eastern-road-patrols",
          "once": false
        }
      ]
    },
    {
      "id": "east-road",
      "name": "Lou Sang East Road",
      "width": 24,
      "height": 14,
      "tileWidth": 16,
      "tileHeight": 16,
      "tileLayers": [
        {
          "id": "ground",
          "name": "Ground",
          "width": 24,
          "height": 14,
          "tiles": [
            3,3,3,3,3,3,3,3,3,3,3,3,3,3,3,3,3,3,3,3,3,3,3,3,
            3,1,1,1,1,1,1,1,1,1,1,1,1,1,1,1,1,1,1,1,1,1,1,3,
            3,1,1,1,1,1,1,1,1,1,1,1,1,1,1,1,1,1,1,1,1,1,1,3,
            3,1,1,1,1,1,1,1,1,1,4,4,4,4,4,1,1,1,1,1,1,1,1,3,
            3,1,1,1,1,1,1,1,1,1,4,4,4,4,4,1,1,1,1,1,1,1,1,3,
            3,1,1,1,1,1,1,1,1,1,4,4,4,4,4,1,1,1,1,1,1,1,1,3,
            3,1,1,1,1,1,1,1,1,1,1,1,1,1,1,1,1,1,1,1,1,1,1,3,
            3,2,2,2,2,2,2,2,2,2,2,2,2,2,2,2,2,2,2,2,2,2,2,3,
            3,1,1,1,1,1,1,1,1,1,1,1,1,1,1,1,1,1,1,1,1,1,1,3,
            3,1,1,1,1,1,1,1,1,1,1,1,1,1,1,1,1,1,3,3,3,1,1,3,
            3,1,1,1,1,1,1,1,1,1,1,1,1,1,1,1,1,1,3,3,3,1,1,3,
            3,1,1,1,1,1,1,1,1,1,1,1,1,1,1,1,1,1,1,1,1,1,1,3,
            3,1,1,1,1,1,1,1,1,1,1,1,1,1,1,1,1,1,1,1,1,1,1,3,
            3,3,3,3,3,3,3,3,3,3,3,3,3,3,3,3,3,3,3,3,3,3,3,3
          ]
        }
      ],
      "collisionLayers": [
        {
          "id": "collision",
          "name": "Collision",
          "width": 24,
          "height": 14,
          "blocked": [
            1,1,1,1,1,1,1,1,1,1,1,1,1,1,1,1,1,1,1,1,1,1,1,1,
            1,0,0,0,0,0,0,0,0,0,0,0,0,0,0,0,0,0,0,0,0,0,0,1,
            1,0,0,0,0,0,0,0,0,0,0,0,0,0,0,0,0,0,0,0,0,0,0,1,
            1,0,0,0,0,0,0,0,0,0,1,1,1,1,1,0,0,0,0,0,0,0,0,1,
            1,0,0,0,0,0,0,0,0,0,1,1,1,1,1,0,0,0,0,0,0,0,0,1,
            1,0,0,0,0,0,0,0,0,0,1,1,1,1,1,0,0,0,0,0,0,0,0,1,
            1,0,0,0,0,0,0,0,0,0,0,0,0,0,0,0,0,0,0,0,0,0,0,1,
            1,0,0,0,0,0,0,0,0,0,0,0,0,0,0,0,0,0,0,0,0,0,0,1,
            1,0,0,0,0,0,0,0,0,0,0,0,0,0,0,0,0,0,0,0,0,0,0,1,
            1,0,0,0,0,0,0,0,0,0,0,0,0,0,0,0,0,0,1,1,1,0,0,1,
            1,0,0,0,0,0,0,0,0,0,0,0,0,0,0,0,0,0,1,1,1,0,0,1,
            1,0,0,0,0,0,0,0,0,0,0,0,0,0,0,0,0,0,0,0,0,0,0,1,
            1,0,0,0,0,0,0,0,0,0,0,0,0,0,0,0,0,0,0,0,0,0,0,1,
            1,1,1,1,1,1,1,1,1,1,1,1,1,1,1,1,1,1,1,1,1,1,1,1
          ]
        }
      ],
      "portals": [
        {
          "id": "east-road-to-field",
          "x": 1,
          "y": 7,
          "width": 1,
          "height": 1,
          "targetMapId": "field",
          "targetSpawnId": "from-east-road"
        },
        {
          "id": "east-road-to-relay-post",
          "x": 22,
          "y": 7,
          "width": 1,
          "height": 1,
          "targetMapId": "relay-post",
          "targetSpawnId": "relay-west-gate"
        }
      ],
      "spawnPoints": [
        {
          "id": "from-field-east",
          "x": 2,
          "y": 7,
          "facing": "right"
        },
        {
          "id": "from-relay-post",
          "x": 20,
          "y": 7,
          "facing": "left"
        }
      ],
      "npcs": [
        {
          "id": "road-scout",
          "name": "巡路兵",
          "x": 11,
          "y": 6,
          "sprite": "guard",
          "facing": "down",
          "behavior": "idle"
        }
      ],
      "triggers": [
        {
          "id": "road-scout-trigger",
          "kind": "npcInteraction",
          "npcId": "road-scout",
          "eventId": "road-scout-event",
          "once": false
        },
        {
          "id": "east-road-battle-trigger",
          "kind": "region",
          "x": 14,
          "y": 6,
          "width": 4,
          "height": 3,
          "encounterTableId": "relay-road-wolves",
          "once": false
        }
      ]
    },
    {
      "id": "relay-post",
      "name": "East Relay Post",
      "width": 18,
      "height": 12,
      "tileWidth": 16,
      "tileHeight": 16,
      "tileLayers": [
        {
          "id": "ground",
          "name": "Ground",
          "width": 18,
          "height": 12,
          "tiles": [
            3,3,3,3,3,3,3,3,3,3,3,3,3,3,3,3,3,3,
            3,1,1,1,1,1,1,1,1,1,1,1,1,1,1,1,1,3,
            3,1,1,1,1,1,1,1,1,1,1,1,1,1,1,1,1,3,
            3,1,1,1,3,3,3,1,1,1,1,3,3,3,1,1,1,3,
            3,1,1,1,3,3,3,1,1,1,1,3,3,3,1,1,1,3,
            3,1,1,1,1,1,1,1,1,1,1,1,1,1,1,1,1,3,
            3,2,2,2,2,2,2,2,2,2,2,2,2,2,2,2,2,3,
            3,1,1,1,1,1,1,1,1,1,1,1,1,1,1,1,1,3,
            3,1,1,1,1,1,1,1,1,1,1,1,1,1,1,1,1,3,
            3,1,1,1,3,3,1,1,1,1,1,1,3,3,1,1,1,3,
            3,1,1,1,1,1,1,1,1,1,1,1,1,1,1,1,1,3,
            3,3,3,3,3,3,3,3,3,3,3,3,3,3,3,3,3,3
          ]
        }
      ],
      "collisionLayers": [
        {
          "id": "collision",
          "name": "Collision",
          "width": 18,
          "height": 12,
          "blocked": [
            1,1,1,1,1,1,1,1,1,1,1,1,1,1,1,1,1,1,
            1,0,0,0,0,0,0,0,0,0,0,0,0,0,0,0,0,1,
            1,0,0,0,0,0,0,0,0,0,0,0,0,0,0,0,0,1,
            1,0,0,0,1,1,1,0,0,0,0,1,1,1,0,0,0,1,
            1,0,0,0,1,1,1,0,0,0,0,1,1,1,0,0,0,1,
            1,0,0,0,0,0,0,0,0,0,0,0,0,0,0,0,0,1,
            1,0,0,0,0,0,0,0,0,0,0,0,0,0,0,0,0,1,
            1,0,0,0,0,0,0,0,0,0,0,0,0,0,0,0,0,1,
            1,0,0,0,0,0,0,0,0,0,0,0,0,0,0,0,0,1,
            1,0,0,0,1,1,0,0,0,0,0,0,1,1,0,0,0,1,
            1,0,0,0,0,0,0,0,0,0,0,0,0,0,0,0,0,1,
            1,1,1,1,1,1,1,1,1,1,1,1,1,1,1,1,1,1
          ]
        }
      ],
      "portals": [
        {
          "id": "relay-post-to-east-road",
          "x": 1,
          "y": 6,
          "width": 1,
          "height": 1,
          "targetMapId": "east-road",
          "targetSpawnId": "from-relay-post"
        }
      ],
      "spawnPoints": [
        {
          "id": "relay-west-gate",
          "x": 2,
          "y": 6,
          "facing": "right"
        }
      ],
      "npcs": [
        {
          "id": "relay-healer",
          "name": "驿站医官",
          "x": 8,
          "y": 6,
          "sprite": "merchant",
          "facing": "left",
          "behavior": "idle"
        },
        {
          "id": "relay-porter",
          "name": "驿卒",
          "x": 11,
          "y": 7,
          "sprite": "guide",
          "facing": "down",
          "behavior": "idle"
        }
      ],
      "triggers": [
        {
          "id": "relay-rest-trigger",
          "kind": "npcInteraction",
          "npcId": "relay-healer",
          "eventId": "relay-rest-event",
          "once": false
        },
        {
          "id": "relay-cache-trigger",
          "kind": "tile",
          "x": 3,
          "y": 9,
          "width": 1,
          "height": 1,
          "eventId": "relay-cache-event",
          "once": true
        }
      ]
    }
  ],
  "items": [
    {
      "id": "travel-pass",
      "name": "路引",
      "description": "盖有楼桑印记的出村路引，守门兵验过后才会放行。",
      "kind": "key",
      "price": 0
    },
    {
      "id": "herb",
      "name": "Herb",
      "description": "Restores a small amount of HP.",
      "kind": "consumable",
      "price": 10
    },
    {
      "id": "bronze-sword",
      "name": "Bronze Sword",
      "description": "A simple bronze blade issued to outpost recruits.",
      "kind": "equipment",
      "price": 45
    }
  ],
  "partyMembers": [
    {
      "id": "liu-bei",
      "name": "Liu Bei",
      "className": "Lord",
      "level": 1,
      "skills": ["focus"],
      "baseStats": {
        "maxHp": 24,
        "maxMp": 6,
        "attack": 9,
        "defense": 7,
        "speed": 5
      }
    }
  ],
  "skills": [
    {
      "id": "focus",
      "name": "Focus",
      "description": "Take a disciplined stance.",
      "mpCost": 0,
      "power": 0,
      "target": "self"
    },
    {
      "id": "slash",
      "name": "Slash",
      "description": "A basic physical attack technique.",
      "mpCost": 0,
      "power": 5,
      "target": "enemy"
    }
  ],
  "flags": [
    {
      "id": "intro-complete",
      "defaultValue": false
    },
    {
      "id": "merchant-met",
      "defaultValue": false
    },
    {
      "id": "gate-pass",
      "defaultValue": false
    },
    {
      "id": "lou-sang-east-gate-open",
      "defaultValue": false
    },
    {
      "id": "town-chest-opened",
      "defaultValue": false
    },
    {
      "id": "relay-cache-opened",
      "defaultValue": false
    }
  ],
  "questStates": [
    {
      "id": "training-yard",
      "stages": ["not-started", "started", "cleared"],
      "initialStage": "not-started"
    }
  ],
  "encounterTables": [
    {
      "id": "eastern-road-patrols",
      "name": "楼桑东路巡逻队",
      "stepInterval": 2,
      "chance": 0.55,
      "entries": [
        {
          "id": "lou-sang-patrol-entry",
          "battleGroupId": "training-slimes",
          "weight": 1
        }
      ]
    },
    {
      "id": "relay-road-wolves",
      "name": "驿道野狼",
      "stepInterval": 3,
      "chance": 1,
      "entries": [
        {
          "id": "relay-road-wolf-entry",
          "battleGroupId": "field-wolves",
          "weight": 1
        }
      ]
    }
  ]
}
